user22/.ipynb_checkpoints/addition-checkpoint.py
user22/.ipynb_checkpoints/subtraction-checkpoint.py
user22/__init__.py
user22/addition.py
user22/subtraction.py
user22-0.1.0.dist-info/METADATA
user22-0.1.0.dist-info/WHEEL
user22-0.1.0.dist-info/RECORD
