Metadata-Version: 2.3
Name: user22
Version: 0.1.0
Summary: training in koreabio
Author: F13F
Author-email: zeho825@gmail.com
Requires-Python: >=3.13
Classifier: Programming Language :: Python :: 3
Classifier: Programming Language :: Python :: 3.13
